distrel/__init__.py
distrel/distrel.py
distrel-0.2.1.dist-info/LICENSE
distrel-0.2.1.dist-info/METADATA
distrel-0.2.1.dist-info/WHEEL
distrel-0.2.1.dist-info/RECORD
