Metadata-Version: 2.1
Name: distrel
Version: 0.2.1
Summary: Calculate the relationship between parameters with known distributions.
License: AGPL-3.0-or-later
Author: Alex
Author-email: adrysdale@protonmail.com
Requires-Python: >=3.11,<4.0
Classifier: License :: OSI Approved :: GNU Affero General Public License v3 or later (AGPLv3+)
Classifier: Programming Language :: Python :: 3
Classifier: Programming Language :: Python :: 3.11
Classifier: Programming Language :: Python :: 3.12
Requires-Dist: nevergrad (>=1.0.1,<2.0.0)
Requires-Dist: scipy (>=1.11.4,<2.0.0)
Requires-Dist: torch (>=2.1.1,<3.0.0)
Requires-Dist: tqdm (>=4.66.1,<5.0.0)
